wise_client/__init__.py
wise_client/base_client.py
wise_client/wise_client.py
wise_client-0.0.2a0.dist-info/LICENSE
wise_client-0.0.2a0.dist-info/METADATA
wise_client-0.0.2a0.dist-info/WHEEL
wise_client-0.0.2a0.dist-info/top_level.txt
wise_client-0.0.2a0.dist-info/RECORD
