Metadata-Version: 2.1
Name: wise-client
Version: 0.0.2a0
Summary: An asynchronous HTTP API wrapper for the Wise API
Author: Chen Kang Yang
License: Apache License
Project-URL: repository, https://github.com/chen-ky/wise-client
Keywords: wise,transferwise,async,REST API,api,exchange rate,currency,finance
Classifier: Programming Language :: Python :: 3
Classifier: License :: OSI Approved :: Apache Software License
Classifier: Development Status :: 3 - Alpha
Classifier: Intended Audience :: Developers
Classifier: Topic :: Software Development :: Libraries :: Python Modules
Requires-Python: >=3.9
License-File: LICENSE
Requires-Dist: anyio (==3.6.2)
Requires-Dist: certifi (==2022.12.7)
Requires-Dist: h11 (==0.14.0)
Requires-Dist: h2 (==4.1.0)
Requires-Dist: hpack (==4.0.0)
Requires-Dist: httpcore (==0.16.3)
Requires-Dist: httpx (==0.23.3)
Requires-Dist: hyperframe (==6.0.1)
Requires-Dist: idna (==3.4)
Requires-Dist: rfc3986 (==1.5.0)
Requires-Dist: sniffio (==1.3.0)
Provides-Extra: doc
Provides-Extra: test
Requires-Dist: pytest (==7.2.0) ; extra == 'test'
Requires-Dist: pytest-asyncio (==0.20.3) ; extra == 'test'
Requires-Dist: pytest-cov (==4.0.0) ; extra == 'test'
Requires-Dist: pytest-httpx (==0.21.2) ; extra == 'test'
